isp_trace_name_mapping_configs/demand_scenario_mapping.yaml
isp_trace_name_mapping_configs/solar_area_mapping.yaml
isp_trace_name_mapping_configs/solar_project_mapping.yaml
isp_trace_name_mapping_configs/wind_area_mapping.yaml
isp_trace_name_mapping_configs/wind_project_mapping.yaml
isp_trace_parser/__init__.py
isp_trace_parser/construct_reference_year_mapping.py
isp_trace_parser/demand_traces.py
isp_trace_parser/get_data.py
isp_trace_parser/input_validation.py
isp_trace_parser/metadata_extractors.py
isp_trace_parser/solar_traces.py
isp_trace_parser/trace_formatter.py
isp_trace_parser/trace_restructure_helper_functions.py
isp_trace_parser/wind_traces.py
isp_trace_parser-1.0.3.dist-info/licenses/LICENSE
isp_trace_parser-1.0.3.dist-info/METADATA
isp_trace_parser-1.0.3.dist-info/WHEEL
isp_trace_parser-1.0.3.dist-info/top_level.txt
isp_trace_parser-1.0.3.dist-info/RECORD
