Metadata-Version: 2.4
Name: isp-trace-parser
Version: 1.0.3
Summary: A Python package for reformatting and accessing demand, solar, and wind time series data used by the
Author-email: nick-gorman <n.gorman305@gmail.com>, prakaa <abiprakash007@gmail.com>, dylanjmcconnell <dylan.mcconnell@unsw.edu.au>
Requires-Python: >=3.9
License-File: LICENSE
Requires-Dist: polars>=1.7.1
Requires-Dist: pandas>=2.2.2
Requires-Dist: pydantic>=2.9.2
Requires-Dist: joblib>=1.4.2
Dynamic: license-file
